eda_bam-0.4.0.dist-info/METADATA
eda_bam-0.4.0.dist-info/WHEEL
eda_bam-0.4.0.dist-info/entry_points.txt
eda_bam/__init__.py
eda_bam/cli.py
eda_bam-0.4.0.dist-info/RECORD
