Metadata-Version: 2.1
Name: eda-bam
Version: 0.4.0
Summary: Navigating data from one thing to another.
Author-Email: ppabam <tom@diginori.com>
License: MIT
Project-URL: Homepage, https://github.com/ppabam/eda-bam
Project-URL: Issues, https://github.com/ppabam/eda-bam/issues
Requires-Python: >=3.10
Requires-Dist: pandas>=2.2.3
Requires-Dist: president-speech>=0.9.1
Requires-Dist: typer>=0.15.1
